open_rppg-0.1.1.dist-info/licenses/LICENSE
rppg/__init__.py
rppg/main.py
rppg/models.py
rppg/models_code/FacePhys.py
rppg/weights/EfficientPhys.pure.weights.h5
rppg/weights/EfficientPhys.rlap.weights.h5
rppg/weights/FacePhys.rlap.weights.h5
rppg/weights/ME.pure.weights.h5
rppg/weights/ME.rlap.weights.h5
rppg/weights/PhysFormer.pure.weights.h5
rppg/weights/PhysFormer.rlap.weights.h5
rppg/weights/PhysMamba.pure.weights.h5
rppg/weights/PhysMamba.rlap.weights.h5
rppg/weights/RhythmMamba.pure.weights.h5
rppg/weights/RhythmMamba.rlap.weights.h5
rppg/weights/TSCAN.pure.weights.h5
rppg/weights/TSCAN.rlap.weights.h5
rppg/weights/blaze_face.onnx
rppg/weights/blaze_face_full.onnx
rppg/weights/blaze_face_short_range.tflite
rppg/weights/physnet.pure.weights.h5
rppg/weights/physnet.rlap.weights.h5
rppg/weights/state.pkl
open_rppg-0.1.1.dist-info/METADATA
open_rppg-0.1.1.dist-info/WHEEL
open_rppg-0.1.1.dist-info/top_level.txt
open_rppg-0.1.1.dist-info/RECORD
