Metadata-Version: 2.4
Name: open-rppg
Version: 0.1.1
Summary: Open rPPG
Author: Kegang Wang
Classifier: Programming Language :: Python :: 3
Classifier: Programming Language :: Python :: 3.9
Classifier: Programming Language :: Python :: 3.10
Classifier: Programming Language :: Python :: 3.11
Classifier: Programming Language :: Python :: 3.12
Classifier: Programming Language :: Python :: 3.13
Classifier: Programming Language :: Python :: 3 :: Only
Classifier: License :: OSI Approved :: MIT License
Classifier: Operating System :: OS Independent
Requires-Python: >=3.9
License-File: LICENSE
Requires-Dist: heartpy>=1.2
Requires-Dist: jax>=0.4.26
Requires-Dist: keras>=3.5.0
Requires-Dist: onnxruntime>=1.8
Requires-Dist: opencv_python>=4.5.5.64
Requires-Dist: scipy>=1.8
Requires-Dist: einops>=0.8
Requires-Dist: av>=13
Dynamic: author
Dynamic: classifier
Dynamic: description-content-type
Dynamic: license-file
Dynamic: requires-dist
Dynamic: requires-python
Dynamic: summary
